bodma/__init__.py
bodma/operations.py
bodma/parser.py
bodma-0.1.0.dist-info/METADATA
bodma-0.1.0.dist-info/WHEEL
bodma-0.1.0.dist-info/top_level.txt
bodma-0.1.0.dist-info/RECORD
